xbbuild/__init__.py
xbbuild/__main__.py
xbbuild/build_doc.py
xbbuild/config.py
xbbuild/info.py
xbbuild/main.py
xbbuild/sphinx.py
xbbuild/zip_doc.py
xbbuild-0.2.1.dist-info/LICENSE
xbbuild-0.2.1.dist-info/METADATA
xbbuild-0.2.1.dist-info/WHEEL
xbbuild-0.2.1.dist-info/entry_points.txt
xbbuild-0.2.1.dist-info/top_level.txt
xbbuild-0.2.1.dist-info/RECORD
