Metadata-Version: 2.1
Name: xbbuild
Version: 0.2.1
Summary: Python Build utilities
Home-page: https://github.com/exbee49/xbbuild
Author: exbee49
License: WTFPL
Classifier: Development Status :: 4 - Beta
Classifier: Programming Language :: Python :: 3 :: Only
License-File: LICENSE
Requires-Dist: xbutils >=0.7.0
